{
  "_id": "page._business_unit",
  "_type": "page.singlequestion",
  "components": [
    {
      "_id": "page._business_unit--radios.input_auto__11",
      "_type": "radios",
      "items": [
        {
          "_id": "page._business_unit--radios.input_auto__11--radio.HQ",
          "_type": "radio",
          "label": "HQ Platforms & Architecture [Dave Rogers]",
          "value": "HQ"
        },
        {
          "_id": "page._business_unit--radios.input_auto__11--radio.HQ2",
          "_type": "radio",
          "label": "HQ Central & Digital [Helen Mott]",
          "value": "HQ2"
        },
        {
          "_id": "page._business_unit--radios.input_auto__11--radio.HQ3",
          "_type": "radio",
          "label": "HQ Security & Privacy [Amie Alenka]",
          "value": "HQ3"
        },
        {
          "_id": "page._business_unit--radios.input_auto__11--radio.LAA",
          "_type": "radio",
          "label": "LAA [Luke Crosby]",
          "value": "LAA"
        },
        {
          "_id": "page._business_unit--radios.input_auto__11--radio.CICA",
          "_type": "radio",
          "label": "CICA [David Marshall]",
          "value": "CICA"
        },
        {
          "_id": "page._business_unit--radios.input_auto__11--radio.OPG",
          "_type": "radio",
          "label": "OPG  [Jane Fallon]",
          "value": "OPG"
        },
        {
          "_id": "page._business_unit--radios.input_auto__11--radio.HMPPS",
          "_type": "radio",
          "label": "HMPPS [Carol Teece]",
          "value": "HMPPS"
        },
        {
          "_id": "page._business_unit--radios.input_auto__11--radio.CTS",
          "_type": "radio",
          "label": "CTS & Service Ops [Richard Matthews]",
          "value": "CTS"
        }
      ],
      "legend": "Business Unit",
      "name": "input_auto__11"
    }
  ],
  "url": "/business_unit"
}